main.py
builtin/__init__.py
builtin/ingest.py
deprecated/__init__.py
deprecated/catalog.py
deprecated/database.py
deprecated/table.py
driver/__init__.py
driver/common.py
driver/core.py
driver/driver.py
driver/io_handlers.py
driver/packager.py
driver/processors.py
driver/task_executor.py
driver/util.py
driver/aws/__init__.py
driver/aws/datalake_api.py
driver/aws/glue_api.py
driver/aws/providers.py
driver/aws/resolvers.py
driver/schema/1.rc-1/model.json
driver/schema/1.rc-1/product.json
tests/assets/__init__.py
tests/assets/integration_sport_events/__init__.py
tests/assets/integration_sport_events/tasks/__init__.py
tests/assets/integration_sport_events/tasks/custom_aggregate_events.py
tests/assets/tasks/__init__.py
tests/assets/tasks/custom_business_logic.py
tests/aws/__init__.py
tests/aws/test_datalake.py
tests/catalog/__init__.py
tests/catalog/test_catalog.py
data_product_processor-1.0.4.dist-info/LICENSE.txt
data_product_processor-1.0.4.dist-info/METADATA
data_product_processor-1.0.4.dist-info/NOTICES.txt
data_product_processor-1.0.4.dist-info/WHEEL
data_product_processor-1.0.4.dist-info/entry_points.txt
data_product_processor-1.0.4.dist-info/top_level.txt
data_product_processor-1.0.4.dist-info/RECORD
