Metadata-Version: 2.1
Name: data-product-processor
Version: 1.0.4
Summary: The data product processor (dpp) is a library for dynamically creating and executing Apache Spark Jobs based on a declarative description of a data product.
Home-page: https://github.com/aws-samples/dpac-data-product-processor
Author: Amazon Web Services
License: Apache License 2.0
Platform: any
License-File: LICENSE.txt
License-File: NOTICES.txt
Requires-Dist: boto3 (==1.18.34)
Requires-Dist: botocore
Requires-Dist: wheel (==0.38.1)
Requires-Dist: pyyaml (==5.4.1)
Requires-Dist: pydantic
Requires-Dist: quinn
Requires-Dist: boto3-stubs[glue] (==1.18.34)
Requires-Dist: mypy-boto3-glue (==1.18.34)
Requires-Dist: jsonschema (==3.0.2)
Requires-Dist: pyspark (==3.2.0)
Requires-Dist: numpy (>=1.19.5)
